{
  "CountryName": "Spain",
  "Domains": [
    {
      "Name": "adbidgo.com",
      "Rank": 7295
    },
    {
      "Name": "aemet.es",
      "Rank": 2777
    },
    {
      "Name": "aeolservice.es",
      "Rank": 6846
    },
    {
      "Name": "bershka.com",
      "Rank": 5762
    },
    {
      "Name": "bestdateshere22.com",
      "Rank": 6656
    },
    {
      "Name": "cadenaser.com",
      "Rank": 6744
    },
    {
      "Name": "ccma.cat",
      "Rank": 8168
    },
    {
      "Name": "com-fast-macbook.live",
      "Rank": 3002
    },
    {
      "Name": "ctui.in",
      "Rank": 9120
    },
    {
      "Name": "cumlouder.com",
      "Rank": 3874
    },
    {
      "Name": "desbloqueador.org",
      "Rank": 7619
    },
    {
      "Name": "descargas2020.com",
      "Rank": 8670
    },
    {
      "Name": "docplayer.es",
      "Rank": 7720
    },
    {
      "Name": "educamos.com",
      "Rank": 5144
    },
    {
      "Name": "elcorteingles.es",
      "Rank": 2662
    },
    {
      "Name": "eoredi.com",
      "Rank": 2643
    },
    {
      "Name": "euskadi.eus",
      "Rank": 9078
    },
    {
      "Name": "expansion.com",
      "Rank": 4357
    },
    {
      "Name": "fbcdn2.com",
      "Rank": 6742
    },
    {
      "Name": "forocoches.com",
      "Rank": 3599
    },
    {
      "Name": "gamovideo.com",
      "Rank": 7970
    },
    {
      "Name": "gencat.cat",
      "Rank": 4157
    },
    {
      "Name": "guarrasdelporno.xxx",
      "Rank": 6229
    },
    {
      "Name": "gva.es",
      "Rank": 3241
    },
    {
      "Name": "infojobs.net",
      "Rank": 3679
    },
    {
      "Name": "intercambiosvirtuales.org",
      "Rank": 7318
    },
    {
      "Name": "ivoox.com",
      "Rank": 4424
    },
    {
      "Name": "leroymerlin.es",
      "Rank": 4329
    },
    {
      "Name": "mejortorrent.org",
      "Rank": 2599
    },
    {
      "Name": "merylaural.info",
      "Rank": 8835
    },
    {
      "Name": "movistar.es",
      "Rank": 4674
    },
    {
      "Name": "movistarplus.es",
      "Rank": 7368
    },
    {
      "Name": "oyi9f1kbaj.com",
      "Rank": 3912
    },
    {
      "Name": "pasion.com",
      "Rank": 8452
    },
    {
      "Name": "pullandbear.com",
      "Rank": 5911
    },
    {
      "Name": "rae.es",
      "Rank": 4766
    },
    {
      "Name": "rarbgmirror.xyz",
      "Rank": 3777
    },
    {
      "Name": "renfe.com",
      "Rank": 6668
    },
    {
      "Name": "rtve.es",
      "Rank": 2115
    },
    {
      "Name": "ruralvia.com",
      "Rank": 8576
    },
    {
      "Name": "sensacine.com",
      "Rank": 4466
    },
    {
      "Name": "serviporno.com",
      "Rank": 2606
    },
    {
      "Name": "teatroporno.com",
      "Rank": 6008
    },
    {
      "Name": "torrentlocura.com",
      "Rank": 8912
    },
    {
      "Name": "upm.es",
      "Rank": 8202
    },
    {
      "Name": "videospornosos.com",
      "Rank": 8992
    },
    {
      "Name": "weatherblink.com",
      "Rank": 3519
    },
    {
      "Name": "wordreference.com",
      "Rank": 327
    },
    {
      "Name": "xtec.cat",
      "Rank": 7058
    },
    {
      "Name": "xupdatemovies.com",
      "Rank": 9691
    }
  ]
}