{
  "CountryName": "Japan",
  "Domains": [
    {
      "Name": "13dl.net",
      "Rank": 2224
    },
    {
      "Name": "5ch.net",
      "Rank": 855
    },
    {
      "Name": "b9good.com",
      "Rank": 1252
    },
    {
      "Name": "bao315.com",
      "Rank": 3000
    },
    {
      "Name": "biglobe.ne.jp",
      "Rank": 1814
    },
    {
      "Name": "blog.jp",
      "Rank": 527
    },
    {
      "Name": "brightstar.com",
      "Rank": 3041
    },
    {
      "Name": "dlsite.com",
      "Rank": 1787
    },
    {
      "Name": "dmm.co.jp",
      "Rank": 372
    },
    {
      "Name": "doublepimp.com",
      "Rank": 294
    },
    {
      "Name": "endclothing.com",
      "Rank": 4027
    },
    {
      "Name": "epwk.com",
      "Rank": 4070
    },
    {
      "Name": "eroterest.net",
      "Rank": 1605
    },
    {
      "Name": "firestorage.jp",
      "Rank": 4210
    },
    {
      "Name": "gift4you.online",
      "Rank": 3088
    },
    {
      "Name": "gigazine.net",
      "Rank": 1470
    },
    {
      "Name": "hatena.ne.jp",
      "Rank": 957
    },
    {
      "Name": "heydouga.com",
      "Rank": 1316
    },
    {
      "Name": "himado.in",
      "Rank": 1300
    },
    {
      "Name": "indie-news.club",
      "Rank": 3341
    },
    {
      "Name": "itmedia.co.jp",
      "Rank": 1195
    },
    {
      "Name": "jal.co.jp",
      "Rank": 2634
    },
    {
      "Name": "javarchive.com",
      "Rank": 2971
    },
    {
      "Name": "javtorrent.re",
      "Rank": 3181
    },
    {
      "Name": "jin115.com",
      "Rank": 2447
    },
    {
      "Name": "kakaku.com",
      "Rank": 400
    },
    {
      "Name": "livedoor.com",
      "Rank": 342
    },
    {
      "Name": "livedoor.jp",
      "Rank": 405
    },
    {
      "Name": "mhometheater.com",
      "Rank": 4158
    },
    {
      "Name": "mmofreegames.online",
      "Rank": 2289
    },
    {
      "Name": "nextdirect.com",
      "Rank": 4138
    },
    {
      "Name": "nikkansports.com",
      "Rank": 2946
    },
    {
      "Name": "ninjagod.com",
      "Rank": 907
    },
    {
      "Name": "olmsoneenh.info",
      "Rank": 3524
    },
    {
      "Name": "opensubtitles.org",
      "Rank": 1824
    },
    {
      "Name": "popcash.net",
      "Rank": 398
    },
    {
      "Name": "prpops.com",
      "Rank": 3602
    },
    {
      "Name": "radiko.jp",
      "Rank": 3979
    },
    {
      "Name": "rakuten.co.jp",
      "Rank": 122
    },
    {
      "Name": "seesaa.net",
      "Rank": 3015
    },
    {
      "Name": "selfridges.com",
      "Rank": 3357
    },
    {
      "Name": "softbank.jp",
      "Rank": 4109
    },
    {
      "Name": "syosetu.com",
      "Rank": 1568
    },
    {
      "Name": "tsite.jp",
      "Rank": 4074
    },
    {
      "Name": "tvanimemuryoudouga.com",
      "Rank": 3469
    },
    {
      "Name": "uploaded.net",
      "Rank": 1127
    },
    {
      "Name": "watchmygf.to",
      "Rank": 1899
    },
    {
      "Name": "wowkorea.jp",
      "Rank": 3910
    },
    {
      "Name": "xbooks.to",
      "Rank": 2766
    },
    {
      "Name": "zozo.jp",
      "Rank": 2761
    }
  ]
}