{
  "CountryName": "Mali",
  "Domains": [
    {
      "Name": "0759home.com",
      "Rank": 42318
    },
    {
      "Name": "0ruz.ml",
      "Rank": 708042
    },
    {
      "Name": "bamada.net",
      "Rank": 104906
    },
    {
      "Name": "batofi.ml",
      "Rank": 799582
    },
    {
      "Name": "bodol.ml",
      "Rank": 222616
    },
    {
      "Name": "breevis.ml",
      "Rank": 800243
    },
    {
      "Name": "bwvideos.ml",
      "Rank": 800377
    },
    {
      "Name": "dsub.ml",
      "Rank": 63234
    },
    {
      "Name": "enhancedgame.ml",
      "Rank": 989786
    },
    {
      "Name": "fileposts.ml",
      "Rank": 389727
    },
    {
      "Name": "filespost.ml",
      "Rank": 273202
    },
    {
      "Name": "good-search.ml",
      "Rank": 261364
    },
    {
      "Name": "hongxingss.ml",
      "Rank": 58763
    },
    {
      "Name": "iptvsrc.ml",
      "Rank": 322329
    },
    {
      "Name": "isitwednesdaymydudes.ml",
      "Rank": 265215
    },
    {
      "Name": "kirakira.ml",
      "Rank": 132710
    },
    {
      "Name": "liftmytube.ml",
      "Rank": 636733
    },
    {
      "Name": "malibaara.com",
      "Rank": 82075
    },
    {
      "Name": "malijet.com",
      "Rank": 16560
    },
    {
      "Name": "malipages.com",
      "Rank": 65756
    },
    {
      "Name": "maxpleasure.ml",
      "Rank": 277972
    },
    {
      "Name": "mohbaboo-subs.ml",
      "Rank": 221748
    },
    {
      "Name": "onibaku.ml",
      "Rank": 561964
    },
    {
      "Name": "orchidinsurance.ml",
      "Rank": 166795
    },
    {
      "Name": "pmu.ml",
      "Rank": 209449
    },
    {
      "Name": "schematics.ml",
      "Rank": 300187
    },
    {
      "Name": "seoprnews.ml",
      "Rank": 458756
    },
    {
      "Name": "sexobuceta.ml",
      "Rank": 261540
    },
    {
      "Name": "studyalltime.ml",
      "Rank": 857410
    },
    {
      "Name": "sxvideos.ml",
      "Rank": 812901
    },
    {
      "Name": "syslike.ml",
      "Rank": 583991
    },
    {
      "Name": "videosxbr.ml",
      "Rank": 327766
    }
  ]
}